pymchelper/__init__.py
pymchelper/_version.py
pymchelper/averaging.py
pymchelper/axis.py
pymchelper/estimator.py
pymchelper/input_output.py
pymchelper/page.py
pymchelper/run.py
pymchelper/simulator_type.py
pymchelper/executor/__init__.py
pymchelper/executor/options.py
pymchelper/executor/runner.py
pymchelper/flair/Data.py
pymchelper/flair/Input.py
pymchelper/flair/__init__.py
pymchelper/flair/common/__init__.py
pymchelper/flair/common/bmath.py
pymchelper/flair/common/csg.py
pymchelper/flair/common/fortran.py
pymchelper/flair/common/log.py
pymchelper/flair/common/rexx.py
pymchelper/flair/db/card.db
pymchelper/flair/db/card.ini
pymchelper/flair/db/db2ini.r
pymchelper/readers/__init__.py
pymchelper/readers/common.py
pymchelper/readers/fluka.py
pymchelper/readers/topas.py
pymchelper/readers/shieldhit/__init__.py
pymchelper/readers/shieldhit/binary_spec.py
pymchelper/readers/shieldhit/general.py
pymchelper/readers/shieldhit/reader_base.py
pymchelper/readers/shieldhit/reader_bdo2016.py
pymchelper/readers/shieldhit/reader_bdo2019.py
pymchelper/readers/shieldhit/reader_bin2010.py
pymchelper/shieldhit/__init__.py
pymchelper/shieldhit/particle.py
pymchelper/shieldhit/detector/__init__.py
pymchelper/shieldhit/detector/detector_type.py
pymchelper/shieldhit/detector/estimator.py
pymchelper/shieldhit/detector/estimator_type.py
pymchelper/shieldhit/detector/fortran_card.py
pymchelper/shieldhit/detector/geometry.py
pymchelper/utils/__init__.py
pymchelper/utils/mcscripter.py
pymchelper/utils/runmc.py
pymchelper/utils/spline.py
pymchelper/utils/radiotherapy/__init__.py
pymchelper/utils/radiotherapy/plan.py
pymchelper/writers/__init__.py
pymchelper/writers/common.py
pymchelper/writers/excel.py
pymchelper/writers/fortranformatter.py
pymchelper/writers/hdf.py
pymchelper/writers/inspector.py
pymchelper/writers/json.py
pymchelper/writers/mcpl.py
pymchelper/writers/plots.py
pymchelper/writers/shieldhit.py
pymchelper/writers/sparse.py
pymchelper/writers/trip98cube.py
pymchelper-2.9.2.dist-info/METADATA
pymchelper-2.9.2.dist-info/WHEEL
pymchelper-2.9.2.dist-info/entry_points.txt
pymchelper-2.9.2.dist-info/top_level.txt
pymchelper-2.9.2.dist-info/RECORD
